{
  "enabled": true,
  "profile_defaults": {
    "challenge": false,
    "funded": true
  },
  "default_mode": "SOFT",
  "pet_start_r": 3.0,
  "r_unit_usd": 0.0,
  "base_risk_pct_for_r_unit": 0.01,
  "enable_daily_pet": true,
  "execution_costs": {
    "commission_per_lot_round_trip_usd": 6.0,
    "avg_spread_cost_usd": 1.0,
    "slippage_cost_usd": 1.0,
    "execution_buffer_per_lot_usd": 8.0
  },
  "min_net_profit_usd": 0.5,
  "stages": [
    {"stage": 0, "name": "OFF", "min_gain_r": 0.0, "max_gain_r": 3.0, "lock_fraction": 0.0},
    {"stage": 1, "name": "STAGE_1", "min_gain_r": 3.0, "max_gain_r": 5.0, "lock_fraction": 0.30},
    {"stage": 2, "name": "STAGE_2", "min_gain_r": 5.0, "max_gain_r": 8.0, "lock_fraction": 0.50},
    {"stage": 3, "name": "STAGE_3", "min_gain_r": 8.0, "max_gain_r": 12.0, "lock_fraction": 0.65},
    {"stage": 4, "name": "STAGE_4", "min_gain_r": 12.0, "max_gain_r": null, "lock_fraction": 0.80}
  ],
  "challenge_mode": {
    "progress_trigger_pct": 50.0,
    "lock_fraction_bonus": 0.15
  },
  "endgame_mode": {
    "progress_trigger_pct": 80.0,
    "lock_multiplier": 1.25,
    "bayes_threshold_delta": 0.05,
    "risk_multiplier": 0.75
  },
  "monte_carlo": {
    "trials": [1000, 5000],
    "max_days": 90,
    "random_seed": 42
  },
  "logging": {
    "event_log_path": "logs/pet_events.csv"
  }
}
